[
  {
    "id": 1,
    "name": "PowerFit Gym",
    "category": "Gym",
    "location": "Sydney",
    "price": 45,
    "services": ["Personal Training", "Group Classes", "Sauna", "Pool", "24/7 Access"],
    "vibe": "Performance & Intensity",
    "description": "High-intensity training facility with state-of-the-art equipment",
    "rating": 4.5,
    "image": "https://images.unsplash.com/photo-1571019613454-1cb2f99b2d8b?w=400"
  },
  {
    "id": 2,
    "name": "Zen Yoga Studio",
    "category": "Yoga",
    "location": "Melbourne",
    "price": 35,
    "services": ["Hot Yoga", "Meditation", "Yoga Mats", "Tea Lounge"],
    "vibe": "Calm & Wellness",
    "description": "Peaceful yoga sanctuary in the heart of Melbourne",
    "rating": 4.8,
    "image": "https://images.unsplash.com/photo-1544367567-0f2fcb009e0b?w=400"
  },
  {
    "id": 3,
    "name": "BoxFit Academy",
    "category": "Boxing",
    "location": "Brisbane",
    "price": 40,
    "services": ["Boxing Classes", "Personal Training", "Sparring", "Fitness Testing"],
    "vibe": "Performance & Intensity",
    "description": "Professional boxing training with experienced coaches",
    "rating": 4.6,
    "image": "https://images.unsplash.com/photo-1549719386-74dfcbf7dbed?w=400"
  },
  {
    "id": 4,
    "name": "Pilates Pro",
    "category": "Pilates",
    "location": "Perth",
    "price": 50,
    "services": ["Reformer Pilates", "Mat Pilates", "Private Sessions", "Prenatal Classes"],
    "vibe": "Calm & Wellness",
    "description": "Expert Pilates instruction for all fitness levels",
    "rating": 4.7,
    "image": "https://images.unsplash.com/photo-1571019613454-1cb2f99b2d8b?w=400"
  },
  {
    "id": 5,
    "name": "FitHub Community",
    "category": "Gym",
    "location": "Adelaide",
    "price": 30,
    "services": ["Group Classes", "Childcare", "Nutrition Counseling", "Social Events"],
    "vibe": "Community & Support",
    "description": "Friendly neighborhood gym with strong community focus",
    "rating": 4.4,
    "image": "https://images.unsplash.com/photo-1534438327276-14e5300c3a48?w=400"
  },
  {
    "id": 6,
    "name": "TechFit Studio",
    "category": "Gym",
    "location": "Sydney",
    "price": 55,
    "services": ["VR Workouts", "AI Personal Training", "Wearable Integration", "Smart Equipment"],
    "vibe": "Modern & Tech-Forward",
    "description": "Cutting-edge fitness technology meets traditional training",
    "rating": 4.3,
    "image": "https://images.unsplash.com/photo-1571019613454-1cb2f99b2d8b?w=400"
  },
  {
    "id": 7,
    "name": "FlexLife Fitness",
    "category": "Gym",
    "location": "Gold Coast",
    "price": 25,
    "services": ["Flexible Hours", "Online Classes", "Mobile App", "Home Workouts"],
    "vibe": "Flexibility & Lifestyle",
    "description": "Work out on your schedule with maximum flexibility",
    "rating": 4.2,
    "image": "https://images.unsplash.com/photo-1534438327276-14e5300c3a48?w=400"
  },
  {
    "id": 8,
    "name": "Mindful Movement",
    "category": "Yoga",
    "location": "Canberra",
    "price": 32,
    "services": ["Vinyasa Flow", "Yin Yoga", "Breathwork", "Workshops"],
    "vibe": "Calm & Wellness",
    "description": "Holistic approach to yoga and mindful movement",
    "rating": 4.9,
    "image": "https://images.unsplash.com/photo-1544367567-0f2fcb009e0b?w=400"
  },
  {
    "id": 9,
    "name": "Mindful Movement Canberra",
    "category": "Yoga",
    "location": "Canberra",
    "price": 32,
    "services": ["Vinyasa Flow", "Yin Yoga", "Breathwork", "Workshops"],
    "vibe": "Calm & Wellness",
    "description": "Holistic approach to yoga and mindful movement",
    "rating": 4.9,
    "image": "https://images.unsplash.com/photo-1544367567-0f2fcb009e0b?w=400"
  },  
  {
    "id": 10,
    "name": "Zen Yoga Studio Sydney",
    "category": "Yoga",
    "location": "Sydney",
    "price": 35,
    "services": ["Hot Yoga", "Meditation", "Yoga Mats", "Tea Lounge"],
    "vibe": "Calm & Wellness",
    "description": "Peaceful yoga sanctuary in the heart of Melbourne",
    "rating": 4.8,
    "image": "https://images.unsplash.com/photo-1544367567-0f2fcb009e0b?w=400"
  },
  {
    "id": 11,
    "name": "Pilates Pro Gym",
    "category": "Gym",
    "location": "Perth",
    "price": 50,
    "services": ["Personal Training", "Group Classes", "Sauna", "Pool", "24/7 Access"],
    "vibe": "Calm & Wellness",
    "description": "Expert Pilates instruction for all fitness levels",
    "rating": 4.7,
    "image": "https://images.unsplash.com/photo-1571019613454-1cb2f99b2d8b?w=400"
  },
  {
    "id": 12,
    "name": "CrossFit Central",
    "category": "CrossFit",
    "location": "Melbourne",
    "price": 60,
    "services": ["WOD Classes", "Olympic Lifting", "Gymnastics", "Nutrition Coaching", "Open Gym"],
    "vibe": "Performance & Intensity",
    "description": "High-intensity functional fitness with community support",
    "rating": 4.6,
    "image": "https://images.unsplash.com/photo-1571019613454-1cb2f99b2d8b?w=400"
  },
  {
    "id": 13,
    "name": "DanceFit Studio",
    "category": "Dance",
    "location": "Brisbane",
    "price": 28,
    "services": ["Zumba", "Hip Hop", "Ballet", "Jazz", "Salsa", "Belly Dance"],
    "vibe": "Community & Support",
    "description": "Fun and energetic dance classes for all skill levels",
    "rating": 4.5,
    "image": "https://images.unsplash.com/photo-1508700929628-666bc8bd84ea?w=400"
  },
  {
    "id": 14,
    "name": "AquaFit Swimming",
    "category": "Swimming",
    "location": "Sydney",
    "price": 40,
    "services": ["Swimming Lessons", "Aqua Aerobics", "Water Polo", "Lap Swimming", "Kids Classes"],
    "vibe": "Calm & Wellness",
    "description": "Professional swimming instruction and aquatic fitness",
    "rating": 4.8,
    "image": "https://images.unsplash.com/photo-1530549387789-4c1017266635?w=400"
  },
  {
    "id": 15,
    "name": "Martial Arts Academy",
    "category": "Martial Arts",
    "location": "Adelaide",
    "price": 45,
    "services": ["Karate", "Taekwondo", "Jiu-Jitsu", "Muay Thai", "Self Defense"],
    "vibe": "Performance & Intensity",
    "description": "Traditional and modern martial arts training",
    "rating": 4.7,
    "image": "https://images.unsplash.com/photo-1591291621166-b81121212d2e?w=400"
  },
  {
    "id": 16,
    "name": "CycleFit Studio",
    "category": "Cycling",
    "location": "Perth",
    "price": 35,
    "services": ["Indoor Cycling", "Spin Classes", "Bike Maintenance", "Group Rides", "Virtual Races"],
    "vibe": "Performance & Intensity",
    "description": "High-energy cycling classes and outdoor group rides",
    "rating": 4.4,
    "image": "https://images.unsplash.com/photo-1558618047-3c8c76ca7d13?w=400"
  },
  {
    "id": 17,
    "name": "RockFit Climbing",
    "category": "Climbing",
    "location": "Melbourne",
    "price": 42,
    "services": ["Rock Climbing", "Bouldering", "Belay Training", "Kids Climbing", "Equipment Rental"],
    "vibe": "Performance & Intensity",
    "description": "Indoor rock climbing and bouldering for all levels",
    "rating": 4.9,
    "image": "https://images.unsplash.com/photo-1522163182402-834f871fd851?w=400"
  },
  {
    "id": 18,
    "name": "Tennis Pro Academy",
    "category": "Tennis",
    "location": "Gold Coast",
    "price": 55,
    "services": ["Tennis Lessons", "Court Rental", "Tournaments", "Kids Programs", "Private Coaching"],
    "vibe": "Performance & Intensity",
    "description": "Professional tennis coaching and court facilities",
    "rating": 4.6,
    "image": "https://images.unsplash.com/photo-1554068865-24cecd4e34b8?w=400"
  },
  {
    "id": 19,
    "name": "Wellness Spa & Fitness",
    "category": "Wellness",
    "location": "Canberra",
    "price": 65,
    "services": ["Massage Therapy", "Spa Treatments", "Meditation", "Aromatherapy", "Wellness Coaching"],
    "vibe": "Calm & Wellness",
    "description": "Complete wellness experience with spa and fitness services",
    "rating": 4.8,
    "image": "https://images.unsplash.com/photo-1540555700478-4be289fbecef?w=400"
  },
  {
    "id": 20,
    "name": "Functional Fitness Hub",
    "category": "Functional Training",
    "location": "Brisbane",
    "price": 38,
    "services": ["Kettlebell Training", "TRX", "Battle Ropes", "Sandbag Workouts", "Mobility Training"],
    "vibe": "Performance & Intensity",
    "description": "Functional movement training for real-world strength",
    "rating": 4.5,
    "image": "https://images.unsplash.com/photo-1571019613454-1cb2f99b2d8b?w=400"
  },
  {
    "id": 21,
    "name": "Barre & Ballet Studio",
    "category": "Barre",
    "location": "Sydney",
    "price": 32,
    "services": ["Barre Classes", "Ballet", "Pilates Fusion", "Stretching", "Posture Correction"],
    "vibe": "Calm & Wellness",
    "description": "Elegant barre and ballet classes for strength and grace",
    "rating": 4.7,
    "image": "https://images.unsplash.com/photo-1508700929628-666bc8bd84ea?w=400"
  },
  {
    "id": 22,
    "name": "Outdoor Adventure Fitness",
    "category": "Outdoor Fitness",
    "location": "Adelaide",
    "price": 30,
    "services": ["Bootcamp", "Trail Running", "Outdoor Yoga", "Hiking", "Beach Workouts"],
    "vibe": "Community & Support",
    "description": "Fresh air fitness with outdoor adventure activities",
    "rating": 4.6,
    "image": "https://images.unsplash.com/photo-1571019613454-1cb2f99b2d8b?w=400"
  },
  {
    "id": 23,
    "name": "Senior Fitness Center",
    "category": "Senior Fitness",
    "location": "Perth",
    "price": 25,
    "services": ["Low Impact Classes", "Balance Training", "Chair Yoga", "Social Activities", "Health Monitoring"],
    "vibe": "Community & Support",
    "description": "Specialized fitness programs for active seniors",
    "rating": 4.9,
    "image": "https://images.unsplash.com/photo-1571019613454-1cb2f99b2d8b?w=400"
  },
  {
    "id": 24,
    "name": "Kids Fitness Academy",
    "category": "Kids Fitness",
    "location": "Melbourne",
    "price": 20,
    "services": ["Kids Yoga", "Gymnastics", "Sports Skills", "Fun Games", "Coordination Training"],
    "vibe": "Community & Support",
    "description": "Fun and engaging fitness programs for children",
    "rating": 4.8,
    "image": "https://images.unsplash.com/photo-1508700929628-666bc8bd84ea?w=400"
  },
  {
    "id": 25,
    "name": "Rehab & Recovery Center",
    "category": "Rehabilitation",
    "location": "Sydney",
    "price": 70,
    "services": ["Physical Therapy", "Injury Recovery", "Post-Surgery Rehab", "Pain Management", "Therapeutic Exercise"],
    "vibe": "Calm & Wellness",
    "description": "Professional rehabilitation and recovery services",
    "rating": 4.9,
    "image": "https://images.unsplash.com/photo-1571019613454-1cb2f99b2d8b?w=400"
  }
]
